Metadata-Version: 2.1
Name: sasl3
Version: 0.2.11
Summary: Cyrus-SASL bindings for Python
Home-page: http://github.com/sparkur/python-sasl3
Maintainer: Ruslan Dautkhanov
Maintainer-email: dautkhanov@gmail.com
License: UNKNOWN
Download-URL: https://github.com/sparkur/python-sasl3/archive/v0.2.11.tar.gz
Platform: UNKNOWN
Classifier: Programming Language :: Python :: 3
Classifier: Development Status :: 5 - Production/Stable
Classifier: Intended Audience :: Developers
Classifier: Intended Audience :: System Administrators
Classifier: License :: OSI Approved :: Apache Software License
Classifier: Programming Language :: Python :: 3
Classifier: Programming Language :: Python :: 3.4
Classifier: Programming Language :: Python :: 3.5
Classifier: Programming Language :: Python :: 3.6
Classifier: Programming Language :: Python :: 3.7
Classifier: Programming Language :: Python :: 3.8
